odoo/addons/ecoembes/README.rst
odoo/addons/ecoembes/__init__.py
odoo/addons/ecoembes/__manifest__.py
odoo/addons/ecoembes/data/ecoembes.market.type.csv
odoo/addons/ecoembes/data/ecoembes.material.csv
odoo/addons/ecoembes/data/ecoembes.packaging.csv
odoo/addons/ecoembes/data/ecoembes.sector.csv
odoo/addons/ecoembes/data/ecoembes.submaterial.csv
odoo/addons/ecoembes/i18n/ecoembes.pot
odoo/addons/ecoembes/i18n/es.po
odoo/addons/ecoembes/migrations/13.0.1.2.0/post-migration.py
odoo/addons/ecoembes/models/__init__.py
odoo/addons/ecoembes/models/abstract_ecoembes_mixin.py
odoo/addons/ecoembes/models/ecoembes_market_type.py
odoo/addons/ecoembes/models/ecoembes_material.py
odoo/addons/ecoembes/models/ecoembes_packaging.py
odoo/addons/ecoembes/models/ecoembes_sector.py
odoo/addons/ecoembes/models/ecoembes_submaterial.py
odoo/addons/ecoembes/models/product_composition.py
odoo/addons/ecoembes/models/product_product.py
odoo/addons/ecoembes/models/product_template.py
odoo/addons/ecoembes/models/res_company.py
odoo/addons/ecoembes/readme/CONFIGURE.rst
odoo/addons/ecoembes/readme/CONTRIBUTORS.rst
odoo/addons/ecoembes/readme/DESCRIPTION.rst
odoo/addons/ecoembes/readme/USAGE.rst
odoo/addons/ecoembes/report/__init__.py
odoo/addons/ecoembes/report/account_move_line_ecoembes_report.py
odoo/addons/ecoembes/report/external_layout.xml
odoo/addons/ecoembes/security/groups.xml
odoo/addons/ecoembes/security/ir.model.access.csv
odoo/addons/ecoembes/static/description/icon.png
odoo/addons/ecoembes/static/description/index.html
odoo/addons/ecoembes/tests/__init__.py
odoo/addons/ecoembes/tests/common.py
odoo/addons/ecoembes/tests/test_ecoembes_misc.py
odoo/addons/ecoembes/tests/test_ecoembes_wizard.py
odoo/addons/ecoembes/views/ecoembes_market_type_view.xml
odoo/addons/ecoembes/views/ecoembes_material_view.xml
odoo/addons/ecoembes/views/ecoembes_packaging_view.xml
odoo/addons/ecoembes/views/ecoembes_sector_view.xml
odoo/addons/ecoembes/views/ecoembes_submaterial_view.xml
odoo13_addon_ecoembes-13.0.1.3.0.dist-info/METADATA
odoo13_addon_ecoembes-13.0.1.3.0.dist-info/WHEEL
odoo13_addon_ecoembes-13.0.1.3.0.dist-info/top_level.txt
odoo13_addon_ecoembes-13.0.1.3.0.dist-info/RECORD
