Metadata-Version: 2.1
Name: odoo13-addon-ecoembes
Version: 13.0.1.3.0
Summary: Add some data related to ecoembes.com
Home-page: https://github.com/OCA/l10n-spain
Author: FactorLibre, Tecnativa, Odoo Community Association (OCA)
Author-email: support@odoo-community.org
License: AGPL-3
Platform: UNKNOWN
Classifier: Programming Language :: Python
Classifier: Framework :: Odoo
Classifier: Framework :: Odoo :: 13.0
Classifier: License :: OSI Approved :: GNU Affero General Public License v3
Requires-Python: >=3.5
Requires-Dist: odoo (<13.1dev,>=13.0a)
